{"v":4,"entries":{"modal--default":{"id":"modal--default","title":"Modal","name":"Default","importPath":"./src/components/modal/Modal.stories.tsx","tags":["story"],"type":"story"},"modal--with-styled":{"id":"modal--with-styled","title":"Modal","name":"With Styled","importPath":"./src/components/modal/Modal.stories.tsx","tags":["story"],"type":"story"},"modal-backdrop--default":{"id":"modal-backdrop--default","title":"Modal.Backdrop","name":"Default","importPath":"./src/components/modal/ModalBackdrop.stories.tsx","tags":["story"],"type":"story"},"modal-content--default":{"id":"modal-content--default","title":"Modal.Content","name":"Default","importPath":"./src/components/modal/ModalContent.stories.tsx","tags":["story"],"type":"story"}}}
